ipfs_huggingface_scraper_py/__init__.py
ipfs_huggingface_scraper_py/ipfs_huggingface_scraper.py
ipfs_huggingface_scraper_py-0.0.3.dist-info/LICENSE
ipfs_huggingface_scraper_py-0.0.3.dist-info/METADATA
ipfs_huggingface_scraper_py-0.0.3.dist-info/WHEEL
ipfs_huggingface_scraper_py-0.0.3.dist-info/top_level.txt
ipfs_huggingface_scraper_py-0.0.3.dist-info/RECORD
